

{
  "itemIdentifier": "ogc.cwl.v1_2_1.CWLDefaultTypedConditional",
  "name": "CWLDefaultTypedConditional",
  "itemClass": "schema",
  "abstract": "CWLDefaultTypedConditional",
  "status": "under-development",
  "dateTimeAddition": "2025-09-29T14:14:37.699245",
  "dateOfLastChange": "2025-09-29",
  "register": "ogc-building-block-register",
  "link": "https://www.commonwl.org/v1.2/Workflow.html",
  "version": "1.2.1",
  "tags": [
    "cwl"
  ],
  "shaclShapes": {},
  "dependsOn": [
    "ogc.cwl.v1_2_1.AnyType",
    "ogc.cwl.v1_2_1.CWLTypeSymbols",
    "ogc.cwl.v1_2_1.CWLDefaultLocation",
    "ogc.cwl.v1_2_1.CWLTypeSymbolValues"
  ],
  "schema": {
    "application/yaml": "https://ogcincubator.github.io/bblocks-cwl/build/annotated/cwl/v1_2_1/CWLDefaultTypedConditional/schema.yaml",
    "application/json": "https://ogcincubator.github.io/bblocks-cwl/build/annotated/cwl/v1_2_1/CWLDefaultTypedConditional/schema.json"
  },
  "sourceSchema": "https://ogcincubator.github.io/bblocks-cwl/_sources/v1_2_1/CWLDefaultTypedConditional/schema.yaml",
  "sourceFiles": "https://ogcincubator.github.io/bblocks-cwl/_sources/v1_2_1/CWLDefaultTypedConditional/",
  "rdfData": [],
  "validationPassed": true,
  "description": "Validate that the 'default' value, if specified, is of same type as the CWL 'type'.\nThis avoids over-accepting anything that does not match the intended type.\nHowever, validation limits itself to data literals and arrays.\nNested type and multi-type definitions will validate against 'Any'.\n",
  "annotatedSchema": "$comment: 'Validate that the ''default'' value, if specified, is of same type as the\n  CWL ''type''.\n\n  This avoids over-accepting anything that does not match the intended type.\n\n  However, validation limits itself to data literals and arrays.\n\n  Nested type and multi-type definitions will validate against ''Any''.\n\n  '\nallOf:\n- $comment: Object structure with minimally 'type' and 'default'. Otherwise, no point\n    to continue testing.\n  properties:\n    default:\n      $ref: https://ogcincubator.github.io/bblocks-cwl/build/annotated/cwl/v1_2_1/AnyType/schema.yaml\n    type:\n      $ref: https://ogcincubator.github.io/bblocks-cwl/build/annotated/cwl/v1_2_1/AnyType/schema.yaml\n  required:\n  - type\n  type: object\n- $comment: Explicit null.\n  if:\n    properties:\n      type:\n        const: 'null'\n  then:\n    properties:\n      default:\n        type: 'null'\n- $comment: Required string.\n  if:\n    properties:\n      type:\n        const: string\n  then:\n    properties:\n      default:\n        type: string\n- $comment: Optional string.\n  if:\n    properties:\n      type:\n        const: string?\n  then:\n    properties:\n      default:\n        type:\n        - string\n        - 'null'\n- $comment: Required boolean.\n  if:\n    properties:\n      type:\n        const: boolean\n  then:\n    properties:\n      default:\n        type: boolean\n- $comment: Optional boolean.\n  if:\n    properties:\n      type:\n        enum:\n        - double?\n        - float?\n        - int?\n        - integer?\n        - long?\n  then:\n    properties:\n      default:\n        type:\n        - number\n        - 'null'\n- $comment: Required numeric.\n  if:\n    properties:\n      type:\n        enum:\n        - double\n        - float\n        - int\n        - integer\n        - long\n  then:\n    properties:\n      default:\n        type: number\n- $comment: Optional numeric.\n  if:\n    properties:\n      type:\n        enum:\n        - double?\n        - float?\n        - int?\n        - integer?\n        - long?\n  then:\n    properties:\n      default:\n        type:\n        - number\n        - 'null'\n- $comment: Required enum.\n  if:\n    properties:\n      symbols:\n        $ref: https://ogcincubator.github.io/bblocks-cwl/build/annotated/cwl/v1_2_1/CWLTypeSymbols/schema.yaml\n      type:\n        const: enum\n  then:\n    properties:\n      default:\n        $ref: https://ogcincubator.github.io/bblocks-cwl/build/annotated/cwl/v1_2_1/CWLTypeSymbolValues/schema.yaml\n- $comment: Optional enum.\n  if:\n    properties:\n      symbols:\n        $ref: https://ogcincubator.github.io/bblocks-cwl/build/annotated/cwl/v1_2_1/CWLTypeSymbols/schema.yaml\n      type:\n        const: enum?\n  then:\n    properties:\n      default:\n        oneOf:\n        - $ref: https://ogcincubator.github.io/bblocks-cwl/build/annotated/cwl/v1_2_1/CWLTypeSymbolValues/schema.yaml\n        - type: 'null'\n- $comment: Required File or Directory.\n  if:\n    properties:\n      type:\n        enum:\n        - Directory\n        - File\n  then:\n    properties:\n      default:\n        $ref: https://ogcincubator.github.io/bblocks-cwl/build/annotated/cwl/v1_2_1/CWLDefaultLocation/schema.yaml\n- $comment: Optional File or Directory.\n  if:\n    properties:\n      type:\n        enum:\n        - Directory?\n        - File?\n  then:\n    properties:\n      default:\n        oneOf:\n        - $ref: https://ogcincubator.github.io/bblocks-cwl/build/annotated/cwl/v1_2_1/CWLDefaultLocation/schema.yaml\n        - type: 'null'\n- $comment: Required array of string.\n  if:\n    oneOf:\n    - properties:\n        type:\n          const: string[]\n    - properties:\n        items:\n          const: string\n        type:\n          const: array\n  then:\n    properties:\n      default:\n        items:\n          type: string\n        type: array\n- $comment: Required array of boolean.\n  if:\n    oneOf:\n    - properties:\n        type:\n          const: boolean[]\n    - properties:\n        items:\n          const: boolean\n        type:\n          const: array\n  then:\n    properties:\n      default:\n        items:\n          type: boolean\n        type: array\n- $comment: Required array of numeric.\n  if:\n    oneOf:\n    - properties:\n        type:\n          enum:\n          - double[]\n          - float[]\n          - int[]\n          - integer[]\n          - long[]\n    - properties:\n        items:\n          enum:\n          - double\n          - float\n          - int\n          - integer\n          - long\n        type:\n          const: array\n  then:\n    properties:\n      default:\n        items:\n          type: number\n        type: array\n- $comment: Required anything (single).\n  if:\n    properties:\n      type:\n        const: Any\n  then:\n    properties:\n      default:\n        $comment: Match anything.\n        $ref: https://ogcincubator.github.io/bblocks-cwl/build/annotated/cwl/v1_2_1/AnyType/schema.yaml\n- $comment: Required array of anything.\n  if:\n    properties:\n      type:\n        const: Any[]\n  then:\n    properties:\n      default:\n        $comment: Match anything as long as under array.\n        items:\n          $ref: https://ogcincubator.github.io/bblocks-cwl/build/annotated/cwl/v1_2_1/AnyType/schema.yaml\n        type: array\n",
  "gitRepository": "https://github.com/ogcincubator/bblocks-cwl",
  "gitPath": "_sources/v1_2_1/CWLDefaultTypedConditional"
}